{
    "id-table": "32c69474-c2e1-43b6-acd4-4e87b8cf0c52",
    "language": "ENGLISH",
    "table-rect": "(127.8, 1399.7, 1355.3, 240.3)",
    "PDF-name": "TDS Sadechaf SPE 1539 v1",
    "Page-number": "1",
    "Cells": [
        {
            "id-entry": 0,
            "entry-rect": "(164.4, 1428.4, 634.6, 41.8)",
            "table-semantic-label": "TABLE_CAPTION",
            "table-header": "Yes",
            "content": "Storage Temperature and Shelf-life",
            "Relationships": {
                "up": [
                    1
                ],
                "down": [
                    2
                ]
            }
        },
        {
            "id-entry": 1,
            "entry-rect": "(154.3, 1376.7, 1324.1, 412.7)",
            "table-semantic-label": "FOOTER",
            "table-header": "Yes",
            "content": " ",
            "Relationships": {
                "right": [
                    7,
                    9
                ],
                "down": [
                    0,
                    2,
                    3,
                    5,
                    6,
                    4,
                    8
                ]
            }
        },
        {
            "id-entry": 2,
            "entry-rect": "(177.5, 1501.6, 642.4, 31.3)",
            "table-semantic-label": "KEYWORD",
            "table-header": "Yes",
            "content": "Storage",
            "Relationships": {
                "right": [
                    3
                ],
                "up": [
                    0,
                    1
                ],
                "down": [
                    4
                ]
            }
        },
        {
            "id-entry": 3,
            "entry-rect": "(827.7, 1499, 634.6, 33.9)",
            "table-semantic-label": "LABEL_CONDITION",
            "table-header": "Yes",
            "content": "Temperature",
            "Relationships": {
                "left": [
                    2
                ],
                "up": [
                    1
                ],
                "down": [
                    5
                ]
            }
        },
        {
            "id-entry": 4,
            "entry-rect": "(174.8, 1540.8, 634.6, 26.1)",
            "table-semantic-label": "LABEL_CONDITION",
            "table-header": "Yes",
            "content": "Recommended temperature",
            "Relationships": {
                "right": [
                    5
                ],
                "up": [
                    2,
                    1
                ],
                "down": [
                    8
                ]
            }
        },
        {
            "id-entry": 5,
            "entry-rect": "(827.7, 1540.8, 624.1, 28.7)",
            "table-semantic-label": "VALUE_CONDITION",
            "table-header": "No",
            "content": "O\u00b0C to +10\u00b0C",
            "Relationships": {
                "left": [
                    4
                ],
                "up": [
                    3,
                    1
                ],
                "down": [
                    6
                ]
            }
        },
        {
            "id-entry": 6,
            "entry-rect": "(825.1, 1566.9, 631.9, 33.9)",
            "table-semantic-label": "VALUE_CONDITION",
            "table-header": "No",
            "content": "-20\u00b0C",
            "Relationships": {
                "left": [
                    8
                ],
                "up": [
                    5,
                    1
                ],
                "down": [
                    7
                ]
            }
        },
        {
            "id-entry": 7,
            "entry-rect": "(827.7, 1611.3, 637.2, 26.1)",
            "table-semantic-label": "VALUE_CONDITION",
            "table-header": "No",
            "content": "+10\u00b0C",
            "Relationships": {
                "left": [
                    1,
                    9
                ],
                "up": [
                    6
                ]
            }
        },
        {
            "id-entry": 8,
            "entry-rect": "(169.6, 1574.7, 645, 31.4)",
            "table-semantic-label": "LABEL_CONDITION",
            "table-header": "Yes",
            "content": "Min storage temperature",
            "Relationships": {
                "right": [
                    6
                ],
                "up": [
                    4,
                    1
                ],
                "down": [
                    9
                ]
            }
        },
        {
            "id-entry": 9,
            "entry-rect": "(169.6, 1608.7, 645, 33.9)",
            "table-semantic-label": "LABEL_CONDITION",
            "table-header": "Yes",
            "content": "Max Storage temperature",
            "Relationships": {
                "left": [
                    1
                ],
                "right": [
                    7
                ],
                "up": [
                    8
                ]
            }
        }
    ]
}